{ "Header1.jpg24" : {
    "ID": 24, 
    "_wp_attached_file": "2014/01/Header1.jpg", 
    "_wp_attachment_context": "custom-header", 
    "_wp_attachment_is_custom_header": "expound", 
    "_wp_attachment_metadata": {
        "file": "2014/01/Header1.jpg", 
        "height": 154, 
        "image_meta": {
            "aperture": 0, 
            "camera": "", 
            "caption": "", 
            "copyright": "", 
            "created_timestamp": 0, 
            "credit": "", 
            "focal_length": 0, 
            "iso": 0, 
            "shutter_speed": 0, 
            "title": ""
        }, 
        "sizes": {
            "expound-featured": {
                "file": "Header1-460x154.jpg", 
                "height": 154, 
                "mime-type": "image/jpeg", 
                "width": 460
            }, 
            "expound-mini": {
                "file": "Header1-50x50.jpg", 
                "height": 50, 
                "mime-type": "image/jpeg", 
                "width": 50
            }, 
            "medium": {
                "file": "Header1-300x45.jpg", 
                "height": 45, 
                "mime-type": "image/jpeg", 
                "width": 300
            }, 
            "post-thumbnail": {
                "file": "Header1-220x126.jpg", 
                "height": 126, 
                "mime-type": "image/jpeg", 
                "width": 220
            }, 
            "thumbnail": {
                "file": "Header1-150x150.jpg", 
                "height": 150, 
                "mime-type": "image/jpeg", 
                "width": 150
            }
        }, 
        "width": 1020
    }, 
    "author": "administrator", 
    "date": 1390686156000, 
    "ptype": "attachment", 
    "slug": "header1-jpg", 
    "status": "inherit", 
    "title": "Header1.jpg"
} , "Brooke Headshot37" : {
    "ID": 37, 
    "_edit_last": "1", 
    "_edit_lock": "1390693577:1", 
    "_gallery_link_preserve_click": "remove", 
    "_gallery_link_url": "about-me", 
    "_wp_attached_file": "2014/01/b2819323d6b113a61068a96dfd482162.jpg", 
    "_wp_attachment_image_alt": "Brooke Colburn", 
    "_wp_attachment_metadata": {
        "file": "2014/01/b2819323d6b113a61068a96dfd482162.jpg", 
        "height": 267, 
        "image_meta": {
            "aperture": 0, 
            "camera": "Canon EOS REBEL T3i", 
            "caption": "", 
            "copyright": "", 
            "created_timestamp": 1381776728, 
            "credit": "", 
            "focal_length": "50", 
            "iso": "320", 
            "shutter_speed": "0.0025", 
            "title": ""
        }, 
        "sizes": {
            "expound-featured": {
                "file": "b2819323d6b113a61068a96dfd482162-400x260.jpg", 
                "height": 260, 
                "mime-type": "image/jpeg", 
                "width": 400
            }, 
            "expound-mini": {
                "file": "b2819323d6b113a61068a96dfd482162-50x50.jpg", 
                "height": 50, 
                "mime-type": "image/jpeg", 
                "width": 50
            }, 
            "medium": {
                "file": "b2819323d6b113a61068a96dfd482162-300x200.jpg", 
                "height": 200, 
                "mime-type": "image/jpeg", 
                "width": 300
            }, 
            "post-thumbnail": {
                "file": "b2819323d6b113a61068a96dfd482162-220x126.jpg", 
                "height": 126, 
                "mime-type": "image/jpeg", 
                "width": 220
            }, 
            "thumbnail": {
                "file": "b2819323d6b113a61068a96dfd482162-150x150.jpg", 
                "height": 150, 
                "mime-type": "image/jpeg", 
                "width": 150
            }
        }, 
        "width": 400
    }, 
    "author": "administrator", 
    "date": 1390687637000, 
    "ptype": "attachment", 
    "slug": "b2819323d6b113a61068a96dfd482162", 
    "status": "inherit", 
    "title": "Brooke Headshot"
} , "weddingreel_2.Still00158" : {
    "ID": 58, 
    "_edit_last": "1", 
    "_edit_lock": "1397661914:1", 
    "_gallery_link_preserve_click": "remove", 
    "_gallery_link_url": "wedding-gallery", 
    "_wp_attached_file": "2014/01/weddingreel_2.Still001.jpg", 
    "_wp_attachment_image_alt": "Wedding", 
    "_wp_attachment_metadata": {
        "file": "2014/01/weddingreel_2.Still001.jpg", 
        "height": 1080, 
        "image_meta": {
            "aperture": 0, 
            "camera": "", 
            "caption": "", 
            "copyright": "", 
            "created_timestamp": 0, 
            "credit": "", 
            "focal_length": 0, 
            "iso": 0, 
            "shutter_speed": 0, 
            "title": ""
        }, 
        "sizes": {
            "expound-featured": {
                "file": "weddingreel_2.Still001-460x260.jpg", 
                "height": 260, 
                "mime-type": "image/jpeg", 
                "width": 460
            }, 
            "expound-mini": {
                "file": "weddingreel_2.Still001-50x50.jpg", 
                "height": 50, 
                "mime-type": "image/jpeg", 
                "width": 50
            }, 
            "large": {
                "file": "weddingreel_2.Still001-1024x576.jpg", 
                "height": 576, 
                "mime-type": "image/jpeg", 
                "width": 1024
            }, 
            "medium": {
                "file": "weddingreel_2.Still001-300x168.jpg", 
                "height": 168, 
                "mime-type": "image/jpeg", 
                "width": 300
            }, 
            "post-thumbnail": {
                "file": "weddingreel_2.Still001-220x126.jpg", 
                "height": 126, 
                "mime-type": "image/jpeg", 
                "width": 220
            }, 
            "thumbnail": {
                "file": "weddingreel_2.Still001-150x150.jpg", 
                "height": 150, 
                "mime-type": "image/jpeg", 
                "width": 150
            }
        }, 
        "width": 1920
    }, 
    "author": "administrator", 
    "date": 1390692785000, 
    "ptype": "attachment", 
    "slug": "weddingreel_2-still001", 
    "status": "inherit", 
    "title": "weddingreel_2.Still001"
} , "Michelle_Alex_Engagment.Still00159" : {
    "ID": 59, 
    "_edit_last": "1", 
    "_edit_lock": "1397661959:1", 
    "_gallery_link_preserve_click": "remove", 
    "_gallery_link_url": "engagement", 
    "_wp_attached_file": "2014/01/Michelle_Alex_Engagment.Still001.jpg", 
    "_wp_attachment_metadata": {
        "file": "2014/01/Michelle_Alex_Engagment.Still001.jpg", 
        "height": 1080, 
        "image_meta": {
            "aperture": 0, 
            "camera": "", 
            "caption": "", 
            "copyright": "", 
            "created_timestamp": 0, 
            "credit": "", 
            "focal_length": 0, 
            "iso": 0, 
            "shutter_speed": 0, 
            "title": ""
        }, 
        "sizes": {
            "expound-featured": {
                "file": "Michelle_Alex_Engagment.Still001-460x260.jpg", 
                "height": 260, 
                "mime-type": "image/jpeg", 
                "width": 460
            }, 
            "expound-mini": {
                "file": "Michelle_Alex_Engagment.Still001-50x50.jpg", 
                "height": 50, 
                "mime-type": "image/jpeg", 
                "width": 50
            }, 
            "large": {
                "file": "Michelle_Alex_Engagment.Still001-1024x576.jpg", 
                "height": 576, 
                "mime-type": "image/jpeg", 
                "width": 1024
            }, 
            "medium": {
                "file": "Michelle_Alex_Engagment.Still001-300x168.jpg", 
                "height": 168, 
                "mime-type": "image/jpeg", 
                "width": 300
            }, 
            "post-thumbnail": {
                "file": "Michelle_Alex_Engagment.Still001-220x126.jpg", 
                "height": 126, 
                "mime-type": "image/jpeg", 
                "width": 220
            }, 
            "thumbnail": {
                "file": "Michelle_Alex_Engagment.Still001-150x150.jpg", 
                "height": 150, 
                "mime-type": "image/jpeg", 
                "width": 150
            }
        }, 
        "width": 1920
    }, 
    "author": "administrator", 
    "date": 1390693122000, 
    "ptype": "attachment", 
    "slug": "michelle_alex_engagment-still001", 
    "status": "inherit", 
    "title": "Michelle_Alex_Engagment.Still001"
} , "Michelle_Alex_Engagment.Still00260" : {
    "ID": 60, 
    "_edit_last": "1", 
    "_edit_lock": "1397661972:1", 
    "_gallery_link_preserve_click": "remove", 
    "_gallery_link_url": "engagement", 
    "_wp_attached_file": "2014/01/Michelle_Alex_Engagment.Still002.jpg", 
    "_wp_attachment_image_alt": "Engagement", 
    "_wp_attachment_metadata": {
        "file": "2014/01/Michelle_Alex_Engagment.Still002.jpg", 
        "height": 1080, 
        "image_meta": {
            "aperture": 0, 
            "camera": "", 
            "caption": "", 
            "copyright": "", 
            "created_timestamp": 0, 
            "credit": "", 
            "focal_length": 0, 
            "iso": 0, 
            "shutter_speed": 0, 
            "title": ""
        }, 
        "sizes": {
            "expound-featured": {
                "file": "Michelle_Alex_Engagment.Still002-460x260.jpg", 
                "height": 260, 
                "mime-type": "image/jpeg", 
                "width": 460
            }, 
            "expound-mini": {
                "file": "Michelle_Alex_Engagment.Still002-50x50.jpg", 
                "height": 50, 
                "mime-type": "image/jpeg", 
                "width": 50
            }, 
            "large": {
                "file": "Michelle_Alex_Engagment.Still002-1024x576.jpg", 
                "height": 576, 
                "mime-type": "image/jpeg", 
                "width": 1024
            }, 
            "medium": {
                "file": "Michelle_Alex_Engagment.Still002-300x168.jpg", 
                "height": 168, 
                "mime-type": "image/jpeg", 
                "width": 300
            }, 
            "post-thumbnail": {
                "file": "Michelle_Alex_Engagment.Still002-220x126.jpg", 
                "height": 126, 
                "mime-type": "image/jpeg", 
                "width": 220
            }, 
            "thumbnail": {
                "file": "Michelle_Alex_Engagment.Still002-150x150.jpg", 
                "height": 150, 
                "mime-type": "image/jpeg", 
                "width": 150
            }
        }, 
        "width": 1920
    }, 
    "author": "administrator", 
    "date": 1390693128000, 
    "ptype": "attachment", 
    "slug": "michelle_alex_engagment-still002", 
    "status": "inherit", 
    "title": "Michelle_Alex_Engagment.Still002"
} , "Sequence 01.Still00161" : {
    "ID": 61, 
    "_edit_last": "1", 
    "_edit_lock": "1397661982:1", 
    "_gallery_link_preserve_click": "remove", 
    "_gallery_link_url": "missions", 
    "_wp_attached_file": "2014/01/Sequence-01.Still001.jpg", 
    "_wp_attachment_image_alt": "Missions", 
    "_wp_attachment_metadata": {
        "file": "2014/01/Sequence-01.Still001.jpg", 
        "height": 1080, 
        "image_meta": {
            "aperture": 0, 
            "camera": "", 
            "caption": "", 
            "copyright": "", 
            "created_timestamp": 0, 
            "credit": "", 
            "focal_length": 0, 
            "iso": 0, 
            "shutter_speed": 0, 
            "title": ""
        }, 
        "sizes": {
            "expound-featured": {
                "file": "Sequence-01.Still001-460x260.jpg", 
                "height": 260, 
                "mime-type": "image/jpeg", 
                "width": 460
            }, 
            "expound-mini": {
                "file": "Sequence-01.Still001-50x50.jpg", 
                "height": 50, 
                "mime-type": "image/jpeg", 
                "width": 50
            }, 
            "large": {
                "file": "Sequence-01.Still001-1024x576.jpg", 
                "height": 576, 
                "mime-type": "image/jpeg", 
                "width": 1024
            }, 
            "medium": {
                "file": "Sequence-01.Still001-300x168.jpg", 
                "height": 168, 
                "mime-type": "image/jpeg", 
                "width": 300
            }, 
            "post-thumbnail": {
                "file": "Sequence-01.Still001-220x126.jpg", 
                "height": 126, 
                "mime-type": "image/jpeg", 
                "width": 220
            }, 
            "thumbnail": {
                "file": "Sequence-01.Still001-150x150.jpg", 
                "height": 150, 
                "mime-type": "image/jpeg", 
                "width": 150
            }
        }, 
        "width": 1920
    }, 
    "author": "administrator", 
    "date": 1390693133000, 
    "ptype": "attachment", 
    "slug": "sequence-01-still001", 
    "status": "inherit", 
    "title": "Sequence 01.Still001"
} , "MediaMissions-Vegas128" : {
    "ID": 128, 
    "_edit_last": "1", 
    "_edit_lock": "1397662034:1", 
    "_gallery_link_preserve_click": "remove", 
    "_gallery_link_url": "missions", 
    "_wp_attached_file": "2013/08/tumblr_inline_mrfavg3eSb1s33ogs.jpg", 
    "_wp_attachment_metadata": {
        "file": "2013/08/tumblr_inline_mrfavg3eSb1s33ogs.jpg", 
        "height": 332, 
        "image_meta": {
            "aperture": 5.6, 
            "camera": "NIKON D300", 
            "caption": "", 
            "copyright": "", 
            "created_timestamp": 1375364790, 
            "credit": "", 
            "focal_length": "35", 
            "iso": "1250", 
            "shutter_speed": "0.066666666666667", 
            "title": ""
        }, 
        "sizes": {
            "expound-featured": {
                "file": "tumblr_inline_mrfavg3eSb1s33ogs-460x260.jpg", 
                "height": 260, 
                "mime-type": "image/jpeg", 
                "width": 460
            }, 
            "expound-mini": {
                "file": "tumblr_inline_mrfavg3eSb1s33ogs-50x50.jpg", 
                "height": 50, 
                "mime-type": "image/jpeg", 
                "width": 50
            }, 
            "medium": {
                "file": "tumblr_inline_mrfavg3eSb1s33ogs-300x199.jpg", 
                "height": 199, 
                "mime-type": "image/jpeg", 
                "width": 300
            }, 
            "post-thumbnail": {
                "file": "tumblr_inline_mrfavg3eSb1s33ogs-220x126.jpg", 
                "height": 126, 
                "mime-type": "image/jpeg", 
                "width": 220
            }, 
            "thumbnail": {
                "file": "tumblr_inline_mrfavg3eSb1s33ogs-150x150.jpg", 
                "height": 150, 
                "mime-type": "image/jpeg", 
                "width": 150
            }
        }, 
        "width": 500
    }, 
    "author": "administrator", 
    "date": 1391709324000, 
    "ptype": "attachment", 
    "slug": "tumblr_inline_mrfavg3esb1s33ogs", 
    "status": "inherit", 
    "title": "MediaMissions-Vegas"
} , "KY-XtremeFootball129" : {
    "ID": 129, 
    "_wp_attached_file": "2013/06/tumblr_inline_moqzoa6K6E1qz4rgp.jpg", 
    "_wp_attachment_metadata": {
        "file": "2013/06/tumblr_inline_moqzoa6K6E1qz4rgp.jpg", 
        "height": 272, 
        "image_meta": {
            "aperture": 0, 
            "camera": "", 
            "caption": "", 
            "copyright": "", 
            "created_timestamp": 0, 
            "credit": "", 
            "focal_length": 0, 
            "iso": 0, 
            "shutter_speed": 0, 
            "title": ""
        }, 
        "sizes": {
            "expound-featured": {
                "file": "tumblr_inline_moqzoa6K6E1qz4rgp-460x260.jpg", 
                "height": 260, 
                "mime-type": "image/jpeg", 
                "width": 460
            }, 
            "expound-mini": {
                "file": "tumblr_inline_moqzoa6K6E1qz4rgp-50x50.jpg", 
                "height": 50, 
                "mime-type": "image/jpeg", 
                "width": 50
            }, 
            "medium": {
                "file": "tumblr_inline_moqzoa6K6E1qz4rgp-300x163.jpg", 
                "height": 163, 
                "mime-type": "image/jpeg", 
                "width": 300
            }, 
            "post-thumbnail": {
                "file": "tumblr_inline_moqzoa6K6E1qz4rgp-220x126.jpg", 
                "height": 126, 
                "mime-type": "image/jpeg", 
                "width": 220
            }, 
            "thumbnail": {
                "file": "tumblr_inline_moqzoa6K6E1qz4rgp-150x150.jpg", 
                "height": 150, 
                "mime-type": "image/jpeg", 
                "width": 150
            }
        }, 
        "width": 500
    }, 
    "author": "administrator", 
    "date": 1391709394000, 
    "ptype": "attachment", 
    "slug": "tumblr_inline_moqzoa6k6e1qz4rgp", 
    "status": "inherit", 
    "title": "KY-XtremeFootball"
} , "157" : {
    "ID": 157, 
    "_wp_attached_file": "2014/04/weddingwand.jpg", 
    "_wp_attachment_metadata": {
        "file": "2014/04/weddingwand.jpg", 
        "height": 685, 
        "image_meta": {
            "aperture": 0, 
            "camera": "", 
            "caption": "", 
            "copyright": "", 
            "created_timestamp": 0, 
            "credit": "", 
            "focal_length": 0, 
            "iso": 0, 
            "shutter_speed": 0, 
            "title": ""
        }, 
        "sizes": {
            "expound-featured": {
                "file": "weddingwand-460x260.jpg", 
                "height": 260, 
                "mime-type": "image/jpeg", 
                "width": 460
            }, 
            "expound-mini": {
                "file": "weddingwand-50x50.jpg", 
                "height": 50, 
                "mime-type": "image/jpeg", 
                "width": 50
            }, 
            "medium": {
                "file": "weddingwand-300x256.jpg", 
                "height": 256, 
                "mime-type": "image/jpeg", 
                "width": 300
            }, 
            "post-thumbnail": {
                "file": "weddingwand-220x126.jpg", 
                "height": 126, 
                "mime-type": "image/jpeg", 
                "width": 220
            }, 
            "thumbnail": {
                "file": "weddingwand-150x150.jpg", 
                "height": 150, 
                "mime-type": "image/jpeg", 
                "width": 150
            }
        }, 
        "width": 800
    }, 
    "author": "administrator", 
    "date": 1398352733000, 
    "ptype": "attachment", 
    "slug": "weddingwand", 
    "status": "inherit", 
    "title": ""
} , "{Sarah+Logan+and+Christopher}+Wedding+Preview-HD166" : {
    "ID": 166, 
    "_wp_attached_file": "2014/01/Sarah+Logan+and+Christopher+Wedding+Preview-HD.mp4", 
    "_wp_attachment_metadata": {
        "audio": {
            "bits_per_sample": 16, 
            "channelmode": "stereo", 
            "channels": 2, 
            "codec": "ISO/IEC 14496-3 AAC", 
            "dataformat": "mp4", 
            "lossless": false, 
            "sample_rate": 44100.0
        }, 
        "dataformat": "quicktime", 
        "fileformat": "mp4", 
        "filesize": 26812639, 
        "height": 720, 
        "length": 97, 
        "length_formatted": "1:37", 
        "mime_type": "video/quicktime", 
        "width": 1280
    }, 
    "author": "brooke", 
    "date": 1399312307000, 
    "ptype": "attachment", 
    "slug": "sarahloganandchristopherweddingpreview-hd", 
    "status": "inherit", 
    "title": "{Sarah+Logan+and+Christopher}+Wedding+Preview-HD"
} , "cropped-header.jpg187" : {
    "ID": 187, 
    "_wp_attached_file": "2014/06/cropped-header.jpg", 
    "_wp_attachment_context": "custom-header", 
    "_wp_attachment_is_custom_header": "expound", 
    "_wp_attachment_metadata": {
        "file": "2014/06/cropped-header.jpg", 
        "height": 154, 
        "image_meta": {
            "aperture": 0, 
            "camera": "", 
            "caption": "", 
            "copyright": "", 
            "created_timestamp": 0, 
            "credit": "", 
            "focal_length": 0, 
            "iso": 0, 
            "shutter_speed": 0, 
            "title": ""
        }, 
        "sizes": {
            "expound-featured": {
                "file": "cropped-header-460x154.jpg", 
                "height": 154, 
                "mime-type": "image/jpeg", 
                "width": 460
            }, 
            "expound-mini": {
                "file": "cropped-header-50x50.jpg", 
                "height": 50, 
                "mime-type": "image/jpeg", 
                "width": 50
            }, 
            "medium": {
                "file": "cropped-header-300x45.jpg", 
                "height": 45, 
                "mime-type": "image/jpeg", 
                "width": 300
            }, 
            "post-thumbnail": {
                "file": "cropped-header-220x126.jpg", 
                "height": 126, 
                "mime-type": "image/jpeg", 
                "width": 220
            }, 
            "thumbnail": {
                "file": "cropped-header-150x150.jpg", 
                "height": 150, 
                "mime-type": "image/jpeg", 
                "width": 150
            }
        }, 
        "width": 1020
    }, 
    "author": "brooke", 
    "date": 1403880939000, 
    "ptype": "attachment", 
    "slug": "cropped-header-jpg", 
    "status": "inherit", 
    "title": "cropped-header.jpg"
} , "Screen Shot 2014-07-02 at 10.35.56 AM197" : {
    "ID": 197, 
    "_wp_attached_file": "2014/07/Screen-Shot-2014-07-02-at-10.35.56-AM.png", 
    "_wp_attachment_metadata": {
        "file": "2014/07/Screen-Shot-2014-07-02-at-10.35.56-AM.png", 
        "height": 1032, 
        "image_meta": {
            "aperture": 0, 
            "camera": "", 
            "caption": "", 
            "copyright": "", 
            "created_timestamp": 0, 
            "credit": "", 
            "focal_length": 0, 
            "iso": 0, 
            "shutter_speed": 0, 
            "title": ""
        }, 
        "sizes": {
            "expound-featured": {
                "file": "Screen-Shot-2014-07-02-at-10.35.56-AM-460x260.png", 
                "height": 260, 
                "mime-type": "image/png", 
                "width": 460
            }, 
            "expound-mini": {
                "file": "Screen-Shot-2014-07-02-at-10.35.56-AM-50x50.png", 
                "height": 50, 
                "mime-type": "image/png", 
                "width": 50
            }, 
            "large": {
                "file": "Screen-Shot-2014-07-02-at-10.35.56-AM-1024x560.png", 
                "height": 560, 
                "mime-type": "image/png", 
                "width": 1024
            }, 
            "medium": {
                "file": "Screen-Shot-2014-07-02-at-10.35.56-AM-300x164.png", 
                "height": 164, 
                "mime-type": "image/png", 
                "width": 300
            }, 
            "post-thumbnail": {
                "file": "Screen-Shot-2014-07-02-at-10.35.56-AM-220x126.png", 
                "height": 126, 
                "mime-type": "image/png", 
                "width": 220
            }, 
            "thumbnail": {
                "file": "Screen-Shot-2014-07-02-at-10.35.56-AM-150x150.png", 
                "height": 150, 
                "mime-type": "image/png", 
                "width": 150
            }
        }, 
        "width": 1886
    }, 
    "author": "brooke", 
    "date": 1404311844000, 
    "ptype": "attachment", 
    "slug": "screen-shot-2014-07-02-at-10-35-56-am", 
    "status": "inherit", 
    "title": "Screen Shot 2014-07-02 at 10.35.56 AM"
} , "CameraShy (1 of 1)201" : {
    "ID": 201, 
    "_wp_attached_file": "2014/07/CameraShy-1-of-1.jpg", 
    "_wp_attachment_metadata": {
        "file": "2014/07/CameraShy-1-of-1.jpg", 
        "height": 1331, 
        "image_meta": {
            "aperture": 4.5, 
            "camera": "NIKON D3S", 
            "caption": "", 
            "copyright": "", 
            "created_timestamp": 1344105090, 
            "credit": "", 
            "focal_length": "24", 
            "iso": "4000", 
            "shutter_speed": "0.004", 
            "title": ""
        }, 
        "sizes": {
            "expound-featured": {
                "file": "CameraShy-1-of-1-460x260.jpg", 
                "height": 260, 
                "mime-type": "image/jpeg", 
                "width": 460
            }, 
            "expound-mini": {
                "file": "CameraShy-1-of-1-50x50.jpg", 
                "height": 50, 
                "mime-type": "image/jpeg", 
                "width": 50
            }, 
            "large": {
                "file": "CameraShy-1-of-1-1024x681.jpg", 
                "height": 681, 
                "mime-type": "image/jpeg", 
                "width": 1024
            }, 
            "medium": {
                "file": "CameraShy-1-of-1-300x199.jpg", 
                "height": 199, 
                "mime-type": "image/jpeg", 
                "width": 300
            }, 
            "post-thumbnail": {
                "file": "CameraShy-1-of-1-220x126.jpg", 
                "height": 126, 
                "mime-type": "image/jpeg", 
                "width": 220
            }, 
            "thumbnail": {
                "file": "CameraShy-1-of-1-150x150.jpg", 
                "height": 150, 
                "mime-type": "image/jpeg", 
                "width": 150
            }
        }, 
        "width": 2000
    }, 
    "author": "brooke", 
    "date": 1404316283000, 
    "ptype": "attachment", 
    "slug": "camerashy-1-of-1", 
    "status": "inherit", 
    "title": "CameraShy (1 of 1)"
} , "Shy203" : {
    "ID": 203, 
    "_wp_attached_file": "2014/07/Shy.jpg", 
    "_wp_attachment_metadata": {
        "file": "2014/07/Shy.jpg", 
        "height": 288, 
        "image_meta": {
            "aperture": 0, 
            "camera": "", 
            "caption": "", 
            "copyright": "", 
            "created_timestamp": 0, 
            "credit": "", 
            "focal_length": 0, 
            "iso": 0, 
            "shutter_speed": 0, 
            "title": ""
        }, 
        "sizes": {
            "expound-featured": {
                "file": "Shy-432x260.jpg", 
                "height": 260, 
                "mime-type": "image/jpeg", 
                "width": 432
            }, 
            "expound-mini": {
                "file": "Shy-50x50.jpg", 
                "height": 50, 
                "mime-type": "image/jpeg", 
                "width": 50
            }, 
            "medium": {
                "file": "Shy-300x200.jpg", 
                "height": 200, 
                "mime-type": "image/jpeg", 
                "width": 300
            }, 
            "post-thumbnail": {
                "file": "Shy-220x126.jpg", 
                "height": 126, 
                "mime-type": "image/jpeg", 
                "width": 220
            }, 
            "thumbnail": {
                "file": "Shy-150x150.jpg", 
                "height": 150, 
                "mime-type": "image/jpeg", 
                "width": 150
            }
        }, 
        "width": 432
    }, 
    "author": "brooke", 
    "date": 1404316588000, 
    "ptype": "attachment", 
    "slug": "shy", 
    "status": "inherit", 
    "title": "Shy"
} , "title208" : {
    "ID": 208, 
    "_wp_attached_file": "2014/07/title.jpg", 
    "_wp_attachment_metadata": {
        "file": "2014/07/title.jpg", 
        "height": 245, 
        "image_meta": {
            "aperture": 0, 
            "camera": "", 
            "caption": "", 
            "copyright": "", 
            "created_timestamp": 0, 
            "credit": "", 
            "focal_length": 0, 
            "iso": 0, 
            "shutter_speed": 0, 
            "title": ""
        }, 
        "sizes": {
            "expound-featured": {
                "file": "title-460x245.jpg", 
                "height": 245, 
                "mime-type": "image/jpeg", 
                "width": 460
            }, 
            "expound-mini": {
                "file": "title-50x50.jpg", 
                "height": 50, 
                "mime-type": "image/jpeg", 
                "width": 50
            }, 
            "medium": {
                "file": "title-300x88.jpg", 
                "height": 88, 
                "mime-type": "image/jpeg", 
                "width": 300
            }, 
            "post-thumbnail": {
                "file": "title-220x126.jpg", 
                "height": 126, 
                "mime-type": "image/jpeg", 
                "width": 220
            }, 
            "thumbnail": {
                "file": "title-150x150.jpg", 
                "height": 150, 
                "mime-type": "image/jpeg", 
                "width": 150
            }
        }, 
        "width": 827
    }, 
    "author": "brooke", 
    "date": 1404317637000, 
    "ptype": "attachment", 
    "slug": "title", 
    "status": "inherit", 
    "title": "title"
} , "title211" : {
    "ID": 211, 
    "_wp_attached_file": "2014/07/title1.jpg", 
    "_wp_attachment_metadata": {
        "file": "2014/07/title1.jpg", 
        "height": 245, 
        "image_meta": {
            "aperture": 0, 
            "camera": "", 
            "caption": "", 
            "copyright": "", 
            "created_timestamp": 0, 
            "credit": "", 
            "focal_length": 0, 
            "iso": 0, 
            "shutter_speed": 0, 
            "title": ""
        }, 
        "sizes": {
            "expound-featured": {
                "file": "title1-460x245.jpg", 
                "height": 245, 
                "mime-type": "image/jpeg", 
                "width": 460
            }, 
            "expound-mini": {
                "file": "title1-50x50.jpg", 
                "height": 50, 
                "mime-type": "image/jpeg", 
                "width": 50
            }, 
            "medium": {
                "file": "title1-300x88.jpg", 
                "height": 88, 
                "mime-type": "image/jpeg", 
                "width": 300
            }, 
            "post-thumbnail": {
                "file": "title1-220x126.jpg", 
                "height": 126, 
                "mime-type": "image/jpeg", 
                "width": 220
            }, 
            "thumbnail": {
                "file": "title1-150x150.jpg", 
                "height": 150, 
                "mime-type": "image/jpeg", 
                "width": 150
            }
        }, 
        "width": 827
    }, 
    "author": "brooke", 
    "date": 1404317811000, 
    "ptype": "attachment", 
    "slug": "title-2", 
    "status": "inherit", 
    "title": "title"
} , "title2214" : {
    "ID": 214, 
    "_wp_attached_file": "2014/07/title2.jpg", 
    "_wp_attachment_metadata": {
        "file": "2014/07/title2.jpg", 
        "height": 245, 
        "image_meta": {
            "aperture": 0, 
            "camera": "", 
            "caption": "", 
            "copyright": "", 
            "created_timestamp": 0, 
            "credit": "", 
            "focal_length": 0, 
            "iso": 0, 
            "shutter_speed": 0, 
            "title": ""
        }, 
        "sizes": {
            "expound-featured": {
                "file": "title2-460x245.jpg", 
                "height": 245, 
                "mime-type": "image/jpeg", 
                "width": 460
            }, 
            "expound-mini": {
                "file": "title2-50x50.jpg", 
                "height": 50, 
                "mime-type": "image/jpeg", 
                "width": 50
            }, 
            "medium": {
                "file": "title2-300x88.jpg", 
                "height": 88, 
                "mime-type": "image/jpeg", 
                "width": 300
            }, 
            "post-thumbnail": {
                "file": "title2-220x126.jpg", 
                "height": 126, 
                "mime-type": "image/jpeg", 
                "width": 220
            }, 
            "thumbnail": {
                "file": "title2-150x150.jpg", 
                "height": 150, 
                "mime-type": "image/jpeg", 
                "width": 150
            }
        }, 
        "width": 827
    }, 
    "author": "brooke", 
    "date": 1404318686000, 
    "ptype": "attachment", 
    "slug": "title2", 
    "status": "inherit", 
    "title": "title2"
} , "title216" : {
    "ID": 216, 
    "_wp_attached_file": "2014/07/title3.jpg", 
    "_wp_attachment_metadata": {
        "file": "2014/07/title3.jpg", 
        "height": 245, 
        "image_meta": {
            "aperture": 0, 
            "camera": "", 
            "caption": "", 
            "copyright": "", 
            "created_timestamp": 0, 
            "credit": "", 
            "focal_length": 0, 
            "iso": 0, 
            "shutter_speed": 0, 
            "title": ""
        }, 
        "sizes": {
            "expound-featured": {
                "file": "title3-460x245.jpg", 
                "height": 245, 
                "mime-type": "image/jpeg", 
                "width": 460
            }, 
            "expound-mini": {
                "file": "title3-50x50.jpg", 
                "height": 50, 
                "mime-type": "image/jpeg", 
                "width": 50
            }, 
            "medium": {
                "file": "title3-300x88.jpg", 
                "height": 88, 
                "mime-type": "image/jpeg", 
                "width": 300
            }, 
            "post-thumbnail": {
                "file": "title3-220x126.jpg", 
                "height": 126, 
                "mime-type": "image/jpeg", 
                "width": 220
            }, 
            "thumbnail": {
                "file": "title3-150x150.jpg", 
                "height": 150, 
                "mime-type": "image/jpeg", 
                "width": 150
            }
        }, 
        "width": 827
    }, 
    "author": "brooke", 
    "date": 1404318845000, 
    "ptype": "attachment", 
    "slug": "title-3", 
    "status": "inherit", 
    "title": "title"
} , "Header.jpg247" : {
    "ID": 247, 
    "_wp_attached_file": "2014/07/Header.jpg", 
    "_wp_attachment_context": "custom-header", 
    "_wp_attachment_is_custom_header": "expound", 
    "_wp_attachment_metadata": {
        "file": "2014/07/Header.jpg", 
        "height": 154, 
        "image_meta": {
            "aperture": 0, 
            "camera": "", 
            "caption": "", 
            "copyright": "", 
            "created_timestamp": 0, 
            "credit": "", 
            "focal_length": 0, 
            "iso": 0, 
            "shutter_speed": 0, 
            "title": ""
        }, 
        "sizes": {
            "expound-featured": {
                "file": "Header-460x154.jpg", 
                "height": 154, 
                "mime-type": "image/jpeg", 
                "width": 460
            }, 
            "expound-mini": {
                "file": "Header-50x50.jpg", 
                "height": 50, 
                "mime-type": "image/jpeg", 
                "width": 50
            }, 
            "medium": {
                "file": "Header-300x45.jpg", 
                "height": 45, 
                "mime-type": "image/jpeg", 
                "width": 300
            }, 
            "post-thumbnail": {
                "file": "Header-220x126.jpg", 
                "height": 126, 
                "mime-type": "image/jpeg", 
                "width": 220
            }, 
            "thumbnail": {
                "file": "Header-150x150.jpg", 
                "height": 150, 
                "mime-type": "image/jpeg", 
                "width": 150
            }
        }, 
        "width": 1020
    }, 
    "author": "brooke", 
    "date": 1404929422000, 
    "ptype": "attachment", 
    "slug": "header-jpg", 
    "status": "inherit", 
    "title": "Header.jpg"
} , "Welcome252" : {
    "ID": 252, 
    "_wp_attached_file": "2014/01/Welcome.jpg", 
    "_wp_attachment_metadata": {
        "file": "2014/01/Welcome.jpg", 
        "height": 154, 
        "image_meta": {
            "aperture": 0, 
            "camera": "", 
            "caption": "", 
            "copyright": "", 
            "created_timestamp": 0, 
            "credit": "", 
            "focal_length": 0, 
            "iso": 0, 
            "shutter_speed": 0, 
            "title": ""
        }, 
        "sizes": {
            "expound-featured": {
                "file": "Welcome-460x154.jpg", 
                "height": 154, 
                "mime-type": "image/jpeg", 
                "width": 460
            }, 
            "expound-mini": {
                "file": "Welcome-50x50.jpg", 
                "height": 50, 
                "mime-type": "image/jpeg", 
                "width": 50
            }, 
            "medium": {
                "file": "Welcome-300x45.jpg", 
                "height": 45, 
                "mime-type": "image/jpeg", 
                "width": 300
            }, 
            "post-thumbnail": {
                "file": "Welcome-220x126.jpg", 
                "height": 126, 
                "mime-type": "image/jpeg", 
                "width": 220
            }, 
            "thumbnail": {
                "file": "Welcome-150x150.jpg", 
                "height": 150, 
                "mime-type": "image/jpeg", 
                "width": 150
            }
        }, 
        "width": 1020
    }, 
    "author": "brooke", 
    "date": 1405000514000, 
    "ptype": "attachment", 
    "slug": "welcome", 
    "status": "inherit", 
    "title": "Welcome"
} , "cropped-Header.png253" : {
    "ID": 253, 
    "_wp_attached_file": "2014/07/cropped-Header.png", 
    "_wp_attachment_context": "custom-header", 
    "_wp_attachment_is_custom_header": "expound", 
    "_wp_attachment_metadata": {
        "file": "2014/07/cropped-Header.png", 
        "height": 154, 
        "image_meta": {
            "aperture": 0, 
            "camera": "", 
            "caption": "", 
            "copyright": "", 
            "created_timestamp": 0, 
            "credit": "", 
            "focal_length": 0, 
            "iso": 0, 
            "shutter_speed": 0, 
            "title": ""
        }, 
        "sizes": {
            "expound-featured": {
                "file": "cropped-Header-460x154.png", 
                "height": 154, 
                "mime-type": "image/png", 
                "width": 460
            }, 
            "expound-mini": {
                "file": "cropped-Header-50x50.png", 
                "height": 50, 
                "mime-type": "image/png", 
                "width": 50
            }, 
            "medium": {
                "file": "cropped-Header-300x45.png", 
                "height": 45, 
                "mime-type": "image/png", 
                "width": 300
            }, 
            "post-thumbnail": {
                "file": "cropped-Header-220x126.png", 
                "height": 126, 
                "mime-type": "image/png", 
                "width": 220
            }, 
            "thumbnail": {
                "file": "cropped-Header-150x150.png", 
                "height": 150, 
                "mime-type": "image/png", 
                "width": 150
            }
        }, 
        "width": 1020
    }, 
    "author": "brooke", 
    "date": 1405000619000, 
    "ptype": "attachment", 
    "slug": "cropped-header-png", 
    "status": "inherit", 
    "title": "cropped-Header.png"
} , "films254" : {
    "ID": 254, 
    "_wp_attached_file": "2014/01/films.jpg", 
    "_wp_attachment_metadata": {
        "file": "2014/01/films.jpg", 
        "height": 154, 
        "image_meta": {
            "aperture": 0, 
            "camera": "", 
            "caption": "", 
            "copyright": "", 
            "created_timestamp": 0, 
            "credit": "", 
            "focal_length": 0, 
            "iso": 0, 
            "shutter_speed": 0, 
            "title": ""
        }, 
        "sizes": {
            "expound-featured": {
                "file": "films-460x154.jpg", 
                "height": 154, 
                "mime-type": "image/jpeg", 
                "width": 460
            }, 
            "expound-mini": {
                "file": "films-50x50.jpg", 
                "height": 50, 
                "mime-type": "image/jpeg", 
                "width": 50
            }, 
            "medium": {
                "file": "films-300x45.jpg", 
                "height": 45, 
                "mime-type": "image/jpeg", 
                "width": 300
            }, 
            "post-thumbnail": {
                "file": "films-220x126.jpg", 
                "height": 126, 
                "mime-type": "image/jpeg", 
                "width": 220
            }, 
            "thumbnail": {
                "file": "films-150x150.jpg", 
                "height": 150, 
                "mime-type": "image/jpeg", 
                "width": 150
            }
        }, 
        "width": 1020
    }, 
    "author": "brooke", 
    "date": 1405001209000, 
    "ptype": "attachment", 
    "slug": "films", 
    "status": "inherit", 
    "title": "films"
} , "films255" : {
    "ID": 255, 
    "_wp_attached_file": "2014/01/films1.jpg", 
    "_wp_attachment_metadata": {
        "file": "2014/01/films1.jpg", 
        "height": 154, 
        "image_meta": {
            "aperture": 0, 
            "camera": "", 
            "caption": "", 
            "copyright": "", 
            "created_timestamp": 0, 
            "credit": "", 
            "focal_length": 0, 
            "iso": 0, 
            "shutter_speed": 0, 
            "title": ""
        }, 
        "sizes": {
            "expound-featured": {
                "file": "films1-460x154.jpg", 
                "height": 154, 
                "mime-type": "image/jpeg", 
                "width": 460
            }, 
            "expound-mini": {
                "file": "films1-50x50.jpg", 
                "height": 50, 
                "mime-type": "image/jpeg", 
                "width": 50
            }, 
            "medium": {
                "file": "films1-300x45.jpg", 
                "height": 45, 
                "mime-type": "image/jpeg", 
                "width": 300
            }, 
            "post-thumbnail": {
                "file": "films1-220x126.jpg", 
                "height": 126, 
                "mime-type": "image/jpeg", 
                "width": 220
            }, 
            "thumbnail": {
                "file": "films1-150x150.jpg", 
                "height": 150, 
                "mime-type": "image/jpeg", 
                "width": 150
            }
        }, 
        "width": 1020
    }, 
    "author": "brooke", 
    "date": 1405001297000, 
    "ptype": "attachment", 
    "slug": "films-2", 
    "status": "inherit", 
    "title": "films"
} , "films256" : {
    "ID": 256, 
    "_wp_attached_file": "2014/01/films2.jpg", 
    "_wp_attachment_metadata": {
        "file": "2014/01/films2.jpg", 
        "height": 154, 
        "image_meta": {
            "aperture": 0, 
            "camera": "", 
            "caption": "", 
            "copyright": "", 
            "created_timestamp": 0, 
            "credit": "", 
            "focal_length": 0, 
            "iso": 0, 
            "shutter_speed": 0, 
            "title": ""
        }, 
        "sizes": {
            "expound-featured": {
                "file": "films2-460x154.jpg", 
                "height": 154, 
                "mime-type": "image/jpeg", 
                "width": 460
            }, 
            "expound-mini": {
                "file": "films2-50x50.jpg", 
                "height": 50, 
                "mime-type": "image/jpeg", 
                "width": 50
            }, 
            "medium": {
                "file": "films2-300x45.jpg", 
                "height": 45, 
                "mime-type": "image/jpeg", 
                "width": 300
            }, 
            "post-thumbnail": {
                "file": "films2-220x126.jpg", 
                "height": 126, 
                "mime-type": "image/jpeg", 
                "width": 220
            }, 
            "thumbnail": {
                "file": "films2-150x150.jpg", 
                "height": 150, 
                "mime-type": "image/jpeg", 
                "width": 150
            }
        }, 
        "width": 1020
    }, 
    "author": "brooke", 
    "date": 1405001369000, 
    "ptype": "attachment", 
    "slug": "films-3", 
    "status": "inherit", 
    "title": "films"
} , "films257" : {
    "ID": 257, 
    "_wp_attached_file": "2014/01/films3.jpg", 
    "_wp_attachment_metadata": {
        "file": "2014/01/films3.jpg", 
        "height": 154, 
        "image_meta": {
            "aperture": 0, 
            "camera": "", 
            "caption": "", 
            "copyright": "", 
            "created_timestamp": 0, 
            "credit": "", 
            "focal_length": 0, 
            "iso": 0, 
            "shutter_speed": 0, 
            "title": ""
        }, 
        "sizes": {
            "expound-featured": {
                "file": "films3-460x154.jpg", 
                "height": 154, 
                "mime-type": "image/jpeg", 
                "width": 460
            }, 
            "expound-mini": {
                "file": "films3-50x50.jpg", 
                "height": 50, 
                "mime-type": "image/jpeg", 
                "width": 50
            }, 
            "medium": {
                "file": "films3-300x45.jpg", 
                "height": 45, 
                "mime-type": "image/jpeg", 
                "width": 300
            }, 
            "post-thumbnail": {
                "file": "films3-220x126.jpg", 
                "height": 126, 
                "mime-type": "image/jpeg", 
                "width": 220
            }, 
            "thumbnail": {
                "file": "films3-150x150.jpg", 
                "height": 150, 
                "mime-type": "image/jpeg", 
                "width": 150
            }
        }, 
        "width": 1020
    }, 
    "author": "brooke", 
    "date": 1405001624000, 
    "ptype": "attachment", 
    "slug": "films-4", 
    "status": "inherit", 
    "title": "films"
} , "engagement259" : {
    "ID": 259, 
    "_wp_attached_file": "2014/01/engagement.jpg", 
    "_wp_attachment_metadata": {
        "file": "2014/01/engagement.jpg", 
        "height": 154, 
        "image_meta": {
            "aperture": 0, 
            "camera": "", 
            "caption": "", 
            "copyright": "", 
            "created_timestamp": 0, 
            "credit": "", 
            "focal_length": 0, 
            "iso": 0, 
            "shutter_speed": 0, 
            "title": ""
        }, 
        "sizes": {
            "expound-featured": {
                "file": "engagement-460x154.jpg", 
                "height": 154, 
                "mime-type": "image/jpeg", 
                "width": 460
            }, 
            "expound-mini": {
                "file": "engagement-50x50.jpg", 
                "height": 50, 
                "mime-type": "image/jpeg", 
                "width": 50
            }, 
            "medium": {
                "file": "engagement-300x45.jpg", 
                "height": 45, 
                "mime-type": "image/jpeg", 
                "width": 300
            }, 
            "post-thumbnail": {
                "file": "engagement-220x126.jpg", 
                "height": 126, 
                "mime-type": "image/jpeg", 
                "width": 220
            }, 
            "thumbnail": {
                "file": "engagement-150x150.jpg", 
                "height": 150, 
                "mime-type": "image/jpeg", 
                "width": 150
            }
        }, 
        "width": 1020
    }, 
    "author": "brooke", 
    "date": 1405001740000, 
    "ptype": "attachment", 
    "slug": "engagement-2", 
    "status": "inherit", 
    "title": "engagement"
} , "films261" : {
    "ID": 261, 
    "_wp_attached_file": "2014/01/films4.jpg", 
    "_wp_attachment_metadata": {
        "file": "2014/01/films4.jpg", 
        "height": 154, 
        "image_meta": {
            "aperture": 0, 
            "camera": "", 
            "caption": "", 
            "copyright": "", 
            "created_timestamp": 0, 
            "credit": "", 
            "focal_length": 0, 
            "iso": 0, 
            "shutter_speed": 0, 
            "title": ""
        }, 
        "sizes": {
            "expound-featured": {
                "file": "films4-460x154.jpg", 
                "height": 154, 
                "mime-type": "image/jpeg", 
                "width": 460
            }, 
            "expound-mini": {
                "file": "films4-50x50.jpg", 
                "height": 50, 
                "mime-type": "image/jpeg", 
                "width": 50
            }, 
            "medium": {
                "file": "films4-300x45.jpg", 
                "height": 45, 
                "mime-type": "image/jpeg", 
                "width": 300
            }, 
            "post-thumbnail": {
                "file": "films4-220x126.jpg", 
                "height": 126, 
                "mime-type": "image/jpeg", 
                "width": 220
            }, 
            "thumbnail": {
                "file": "films4-150x150.jpg", 
                "height": 150, 
                "mime-type": "image/jpeg", 
                "width": 150
            }
        }, 
        "width": 1020
    }, 
    "author": "brooke", 
    "date": 1405001859000, 
    "ptype": "attachment", 
    "slug": "films-5", 
    "status": "inherit", 
    "title": "films"
} , "packages264" : {
    "ID": 264, 
    "_wp_attached_file": "2014/01/packages.jpg", 
    "_wp_attachment_metadata": {
        "file": "2014/01/packages.jpg", 
        "height": 154, 
        "image_meta": {
            "aperture": 0, 
            "camera": "", 
            "caption": "", 
            "copyright": "", 
            "created_timestamp": 0, 
            "credit": "", 
            "focal_length": 0, 
            "iso": 0, 
            "shutter_speed": 0, 
            "title": ""
        }, 
        "sizes": {
            "expound-featured": {
                "file": "packages-460x154.jpg", 
                "height": 154, 
                "mime-type": "image/jpeg", 
                "width": 460
            }, 
            "expound-mini": {
                "file": "packages-50x50.jpg", 
                "height": 50, 
                "mime-type": "image/jpeg", 
                "width": 50
            }, 
            "medium": {
                "file": "packages-300x45.jpg", 
                "height": 45, 
                "mime-type": "image/jpeg", 
                "width": 300
            }, 
            "post-thumbnail": {
                "file": "packages-220x126.jpg", 
                "height": 126, 
                "mime-type": "image/jpeg", 
                "width": 220
            }, 
            "thumbnail": {
                "file": "packages-150x150.jpg", 
                "height": 150, 
                "mime-type": "image/jpeg", 
                "width": 150
            }
        }, 
        "width": 1020
    }, 
    "author": "brooke", 
    "date": 1405002127000, 
    "ptype": "attachment", 
    "slug": "packages-2", 
    "status": "inherit", 
    "title": "packages"
} , "packages266" : {
    "ID": 266, 
    "_wp_attached_file": "2014/01/packages1.jpg", 
    "_wp_attachment_metadata": {
        "file": "2014/01/packages1.jpg", 
        "height": 154, 
        "image_meta": {
            "aperture": 0, 
            "camera": "", 
            "caption": "", 
            "copyright": "", 
            "created_timestamp": 0, 
            "credit": "", 
            "focal_length": 0, 
            "iso": 0, 
            "shutter_speed": 0, 
            "title": ""
        }, 
        "sizes": {
            "expound-featured": {
                "file": "packages1-460x154.jpg", 
                "height": 154, 
                "mime-type": "image/jpeg", 
                "width": 460
            }, 
            "expound-mini": {
                "file": "packages1-50x50.jpg", 
                "height": 50, 
                "mime-type": "image/jpeg", 
                "width": 50
            }, 
            "medium": {
                "file": "packages1-300x45.jpg", 
                "height": 45, 
                "mime-type": "image/jpeg", 
                "width": 300
            }, 
            "post-thumbnail": {
                "file": "packages1-220x126.jpg", 
                "height": 126, 
                "mime-type": "image/jpeg", 
                "width": 220
            }, 
            "thumbnail": {
                "file": "packages1-150x150.jpg", 
                "height": 150, 
                "mime-type": "image/jpeg", 
                "width": 150
            }
        }, 
        "width": 1020
    }, 
    "author": "brooke", 
    "date": 1405002243000, 
    "ptype": "attachment", 
    "slug": "packages-3", 
    "status": "inherit", 
    "title": "packages"
} , "Header1.jpg269" : {
    "ID": 269, 
    "_wp_attached_file": "2014/07/Header1.jpg", 
    "_wp_attachment_context": "custom-header", 
    "author": "brooke", 
    "date": 1405017645000, 
    "ptype": "attachment", 
    "slug": "header1-jpg-2", 
    "status": "inherit", 
    "title": "Header1.jpg"
} , "Header2.jpg270" : {
    "ID": 270, 
    "_wp_attached_file": "2014/07/Header2.jpg", 
    "_wp_attachment_context": "custom-header", 
    "author": "brooke", 
    "date": 1405017723000, 
    "ptype": "attachment", 
    "slug": "header2-jpg", 
    "status": "inherit", 
    "title": "Header2.jpg"
} , "Header271" : {
    "ID": 271, 
    "_wp_attached_file": "2014/07/Header3.jpg", 
    "_wp_attachment_metadata": {
        "file": "2014/07/Header3.jpg", 
        "height": 154, 
        "image_meta": {
            "aperture": 0, 
            "camera": "", 
            "caption": "", 
            "copyright": "", 
            "created_timestamp": 0, 
            "credit": "", 
            "focal_length": 0, 
            "iso": 0, 
            "shutter_speed": 0, 
            "title": ""
        }, 
        "sizes": {
            "expound-featured": {
                "file": "Header3-460x154.jpg", 
                "height": 154, 
                "mime-type": "image/jpeg", 
                "width": 460
            }, 
            "expound-mini": {
                "file": "Header3-50x50.jpg", 
                "height": 50, 
                "mime-type": "image/jpeg", 
                "width": 50
            }, 
            "medium": {
                "file": "Header3-300x45.jpg", 
                "height": 45, 
                "mime-type": "image/jpeg", 
                "width": 300
            }, 
            "post-thumbnail": {
                "file": "Header3-220x126.jpg", 
                "height": 126, 
                "mime-type": "image/jpeg", 
                "width": 220
            }, 
            "thumbnail": {
                "file": "Header3-150x150.jpg", 
                "height": 150, 
                "mime-type": "image/jpeg", 
                "width": 150
            }
        }, 
        "width": 1020
    }, 
    "author": "brooke", 
    "date": 1405017737000, 
    "ptype": "attachment", 
    "slug": "header", 
    "status": "inherit", 
    "title": "Header"
} , "cropped-Header3.jpg272" : {
    "ID": 272, 
    "_wp_attached_file": "2014/07/cropped-Header3.jpg", 
    "_wp_attachment_context": "custom-header", 
    "_wp_attachment_is_custom_header": "expound", 
    "_wp_attachment_metadata": {
        "file": "2014/07/cropped-Header3.jpg", 
        "height": 154, 
        "image_meta": {
            "aperture": 0, 
            "camera": "", 
            "caption": "", 
            "copyright": "", 
            "created_timestamp": 0, 
            "credit": "", 
            "focal_length": 0, 
            "iso": 0, 
            "shutter_speed": 0, 
            "title": ""
        }, 
        "sizes": {
            "expound-featured": {
                "file": "cropped-Header3-460x154.jpg", 
                "height": 154, 
                "mime-type": "image/jpeg", 
                "width": 460
            }, 
            "expound-mini": {
                "file": "cropped-Header3-50x50.jpg", 
                "height": 50, 
                "mime-type": "image/jpeg", 
                "width": 50
            }, 
            "medium": {
                "file": "cropped-Header3-300x45.jpg", 
                "height": 45, 
                "mime-type": "image/jpeg", 
                "width": 300
            }, 
            "post-thumbnail": {
                "file": "cropped-Header3-220x126.jpg", 
                "height": 126, 
                "mime-type": "image/jpeg", 
                "width": 220
            }, 
            "thumbnail": {
                "file": "cropped-Header3-150x150.jpg", 
                "height": 150, 
                "mime-type": "image/jpeg", 
                "width": 150
            }
        }, 
        "width": 1020
    }, 
    "author": "brooke", 
    "date": 1405017747000, 
    "ptype": "attachment", 
    "slug": "cropped-header3-jpg", 
    "status": "inherit", 
    "title": "cropped-Header3.jpg"
} , "Header273" : {
    "ID": 273, 
    "_wp_attached_file": "2014/07/Header4.jpg", 
    "_wp_attachment_metadata": {
        "file": "2014/07/Header4.jpg", 
        "height": 154, 
        "image_meta": {
            "aperture": 0, 
            "camera": "", 
            "caption": "", 
            "copyright": "", 
            "created_timestamp": 0, 
            "credit": "", 
            "focal_length": 0, 
            "iso": 0, 
            "shutter_speed": 0, 
            "title": ""
        }, 
        "sizes": {
            "expound-featured": {
                "file": "Header4-460x154.jpg", 
                "height": 154, 
                "mime-type": "image/jpeg", 
                "width": 460
            }, 
            "expound-mini": {
                "file": "Header4-50x50.jpg", 
                "height": 50, 
                "mime-type": "image/jpeg", 
                "width": 50
            }, 
            "medium": {
                "file": "Header4-300x45.jpg", 
                "height": 45, 
                "mime-type": "image/jpeg", 
                "width": 300
            }, 
            "post-thumbnail": {
                "file": "Header4-220x126.jpg", 
                "height": 126, 
                "mime-type": "image/jpeg", 
                "width": 220
            }, 
            "thumbnail": {
                "file": "Header4-150x150.jpg", 
                "height": 150, 
                "mime-type": "image/jpeg", 
                "width": 150
            }
        }, 
        "width": 1020
    }, 
    "author": "brooke", 
    "date": 1405017863000, 
    "ptype": "attachment", 
    "slug": "header-2", 
    "status": "inherit", 
    "title": "Header"
} , "cropped-Header4.jpg274" : {
    "ID": 274, 
    "_wp_attached_file": "2014/07/cropped-Header4.jpg", 
    "_wp_attachment_context": "custom-header", 
    "_wp_attachment_is_custom_header": "expound", 
    "_wp_attachment_metadata": {
        "file": "2014/07/cropped-Header4.jpg", 
        "height": 154, 
        "image_meta": {
            "aperture": 0, 
            "camera": "", 
            "caption": "", 
            "copyright": "", 
            "created_timestamp": 0, 
            "credit": "", 
            "focal_length": 0, 
            "iso": 0, 
            "shutter_speed": 0, 
            "title": ""
        }, 
        "sizes": {
            "expound-featured": {
                "file": "cropped-Header4-460x154.jpg", 
                "height": 154, 
                "mime-type": "image/jpeg", 
                "width": 460
            }, 
            "expound-mini": {
                "file": "cropped-Header4-50x50.jpg", 
                "height": 50, 
                "mime-type": "image/jpeg", 
                "width": 50
            }, 
            "medium": {
                "file": "cropped-Header4-300x45.jpg", 
                "height": 45, 
                "mime-type": "image/jpeg", 
                "width": 300
            }, 
            "post-thumbnail": {
                "file": "cropped-Header4-220x126.jpg", 
                "height": 126, 
                "mime-type": "image/jpeg", 
                "width": 220
            }, 
            "thumbnail": {
                "file": "cropped-Header4-150x150.jpg", 
                "height": 150, 
                "mime-type": "image/jpeg", 
                "width": 150
            }
        }, 
        "width": 1020
    }, 
    "author": "brooke", 
    "date": 1405017872000, 
    "ptype": "attachment", 
    "slug": "cropped-header4-jpg", 
    "status": "inherit", 
    "title": "cropped-Header4.jpg"
} , "Header275" : {
    "ID": 275, 
    "_wp_attached_file": "2014/07/Header5.jpg", 
    "_wp_attachment_metadata": {
        "file": "2014/07/Header5.jpg", 
        "height": 154, 
        "image_meta": {
            "aperture": 0, 
            "camera": "", 
            "caption": "", 
            "copyright": "", 
            "created_timestamp": 0, 
            "credit": "", 
            "focal_length": 0, 
            "iso": 0, 
            "shutter_speed": 0, 
            "title": ""
        }, 
        "sizes": {
            "expound-featured": {
                "file": "Header5-460x154.jpg", 
                "height": 154, 
                "mime-type": "image/jpeg", 
                "width": 460
            }, 
            "expound-mini": {
                "file": "Header5-50x50.jpg", 
                "height": 50, 
                "mime-type": "image/jpeg", 
                "width": 50
            }, 
            "medium": {
                "file": "Header5-300x45.jpg", 
                "height": 45, 
                "mime-type": "image/jpeg", 
                "width": 300
            }, 
            "post-thumbnail": {
                "file": "Header5-220x126.jpg", 
                "height": 126, 
                "mime-type": "image/jpeg", 
                "width": 220
            }, 
            "thumbnail": {
                "file": "Header5-150x150.jpg", 
                "height": 150, 
                "mime-type": "image/jpeg", 
                "width": 150
            }
        }, 
        "width": 1020
    }, 
    "author": "brooke", 
    "date": 1405018035000, 
    "ptype": "attachment", 
    "slug": "header-3", 
    "status": "inherit", 
    "title": "Header"
} , "cropped-Header5.jpg276" : {
    "ID": 276, 
    "_wp_attached_file": "2014/07/cropped-Header5.jpg", 
    "_wp_attachment_context": "custom-header", 
    "_wp_attachment_is_custom_header": "expound", 
    "_wp_attachment_metadata": {
        "file": "2014/07/cropped-Header5.jpg", 
        "height": 154, 
        "image_meta": {
            "aperture": 0, 
            "camera": "", 
            "caption": "", 
            "copyright": "", 
            "created_timestamp": 0, 
            "credit": "", 
            "focal_length": 0, 
            "iso": 0, 
            "shutter_speed": 0, 
            "title": ""
        }, 
        "sizes": {
            "expound-featured": {
                "file": "cropped-Header5-460x154.jpg", 
                "height": 154, 
                "mime-type": "image/jpeg", 
                "width": 460
            }, 
            "expound-mini": {
                "file": "cropped-Header5-50x50.jpg", 
                "height": 50, 
                "mime-type": "image/jpeg", 
                "width": 50
            }, 
            "medium": {
                "file": "cropped-Header5-300x45.jpg", 
                "height": 45, 
                "mime-type": "image/jpeg", 
                "width": 300
            }, 
            "post-thumbnail": {
                "file": "cropped-Header5-220x126.jpg", 
                "height": 126, 
                "mime-type": "image/jpeg", 
                "width": 220
            }, 
            "thumbnail": {
                "file": "cropped-Header5-150x150.jpg", 
                "height": 150, 
                "mime-type": "image/jpeg", 
                "width": 150
            }
        }, 
        "width": 1020
    }, 
    "author": "brooke", 
    "date": 1405018048000, 
    "ptype": "attachment", 
    "slug": "cropped-header5-jpg", 
    "status": "inherit", 
    "title": "cropped-Header5.jpg"
} , "Screen Shot 2014-07-11 at 10.31.58 AM278" : {
    "ID": 278, 
    "_wp_attached_file": "2014/07/Screen-Shot-2014-07-11-at-10.31.58-AM.png", 
    "_wp_attachment_metadata": {
        "file": "2014/07/Screen-Shot-2014-07-11-at-10.31.58-AM.png", 
        "height": 485, 
        "image_meta": {
            "aperture": 0, 
            "camera": "", 
            "caption": "", 
            "copyright": "", 
            "created_timestamp": 0, 
            "credit": "", 
            "focal_length": 0, 
            "iso": 0, 
            "shutter_speed": 0, 
            "title": ""
        }, 
        "sizes": {
            "expound-featured": {
                "file": "Screen-Shot-2014-07-11-at-10.31.58-AM-460x260.png", 
                "height": 260, 
                "mime-type": "image/png", 
                "width": 460
            }, 
            "expound-mini": {
                "file": "Screen-Shot-2014-07-11-at-10.31.58-AM-50x50.png", 
                "height": 50, 
                "mime-type": "image/png", 
                "width": 50
            }, 
            "medium": {
                "file": "Screen-Shot-2014-07-11-at-10.31.58-AM-300x161.png", 
                "height": 161, 
                "mime-type": "image/png", 
                "width": 300
            }, 
            "post-thumbnail": {
                "file": "Screen-Shot-2014-07-11-at-10.31.58-AM-220x126.png", 
                "height": 126, 
                "mime-type": "image/png", 
                "width": 220
            }, 
            "thumbnail": {
                "file": "Screen-Shot-2014-07-11-at-10.31.58-AM-150x150.png", 
                "height": 150, 
                "mime-type": "image/png", 
                "width": 150
            }
        }, 
        "width": 901
    }, 
    "author": "brooke", 
    "date": 1405089280000, 
    "ptype": "attachment", 
    "slug": "screen-shot-2014-07-11-at-10-31-58-am", 
    "status": "inherit", 
    "title": "Screen Shot 2014-07-11 at 10.31.58 AM"
} , "Baby_1281" : {
    "ID": 281, 
    "_wp_attached_file": "2014/07/Baby_1.jpg", 
    "_wp_attachment_metadata": {
        "file": "2014/07/Baby_1.jpg", 
        "height": 288, 
        "image_meta": {
            "aperture": 0, 
            "camera": "", 
            "caption": "", 
            "copyright": "", 
            "created_timestamp": 0, 
            "credit": "", 
            "focal_length": 0, 
            "iso": 0, 
            "shutter_speed": 0, 
            "title": ""
        }, 
        "sizes": {
            "expound-featured": {
                "file": "Baby_1-432x260.jpg", 
                "height": 260, 
                "mime-type": "image/jpeg", 
                "width": 432
            }, 
            "expound-mini": {
                "file": "Baby_1-50x50.jpg", 
                "height": 50, 
                "mime-type": "image/jpeg", 
                "width": 50
            }, 
            "medium": {
                "file": "Baby_1-300x200.jpg", 
                "height": 200, 
                "mime-type": "image/jpeg", 
                "width": 300
            }, 
            "post-thumbnail": {
                "file": "Baby_1-220x126.jpg", 
                "height": 126, 
                "mime-type": "image/jpeg", 
                "width": 220
            }, 
            "thumbnail": {
                "file": "Baby_1-150x150.jpg", 
                "height": 150, 
                "mime-type": "image/jpeg", 
                "width": 150
            }
        }, 
        "width": 432
    }, 
    "author": "brooke", 
    "date": 1405090641000, 
    "ptype": "attachment", 
    "slug": "baby_1", 
    "status": "inherit", 
    "title": "Baby_1"
} , "Baby284" : {
    "ID": 284, 
    "_wp_attached_file": "2014/07/Baby.jpg", 
    "_wp_attachment_metadata": {
        "file": "2014/07/Baby.jpg", 
        "height": 288, 
        "image_meta": {
            "aperture": 0, 
            "camera": "", 
            "caption": "", 
            "copyright": "", 
            "created_timestamp": 0, 
            "credit": "", 
            "focal_length": 0, 
            "iso": 0, 
            "shutter_speed": 0, 
            "title": ""
        }, 
        "sizes": {
            "expound-featured": {
                "file": "Baby-432x260.jpg", 
                "height": 260, 
                "mime-type": "image/jpeg", 
                "width": 432
            }, 
            "expound-mini": {
                "file": "Baby-50x50.jpg", 
                "height": 50, 
                "mime-type": "image/jpeg", 
                "width": 50
            }, 
            "medium": {
                "file": "Baby-300x200.jpg", 
                "height": 200, 
                "mime-type": "image/jpeg", 
                "width": 300
            }, 
            "post-thumbnail": {
                "file": "Baby-220x126.jpg", 
                "height": 126, 
                "mime-type": "image/jpeg", 
                "width": 220
            }, 
            "thumbnail": {
                "file": "Baby-150x150.jpg", 
                "height": 150, 
                "mime-type": "image/jpeg", 
                "width": 150
            }
        }, 
        "width": 432
    }, 
    "author": "brooke", 
    "date": 1405090732000, 
    "ptype": "attachment", 
    "slug": "baby", 
    "status": "inherit", 
    "title": "Baby"
} , "1_n295" : {
    "ID": 295, 
    "_edit_last": "2", 
    "_edit_lock": "1405107670:2", 
    "_gallery_link_preserve_click": "remove", 
    "_gallery_link_url": "wedding-gallery", 
    "_wp_attached_file": "2014/01/1_n.jpg", 
    "_wp_attachment_metadata": {
        "file": "2014/01/1_n.jpg", 
        "height": 405, 
        "image_meta": {
            "aperture": 0, 
            "camera": "", 
            "caption": "", 
            "copyright": "", 
            "created_timestamp": 0, 
            "credit": "", 
            "focal_length": 0, 
            "iso": 0, 
            "shutter_speed": 0, 
            "title": ""
        }, 
        "sizes": {
            "expound-featured": {
                "file": "1_n-460x260.jpg", 
                "height": 260, 
                "mime-type": "image/jpeg", 
                "width": 460
            }, 
            "expound-mini": {
                "file": "1_n-50x50.jpg", 
                "height": 50, 
                "mime-type": "image/jpeg", 
                "width": 50
            }, 
            "medium": {
                "file": "1_n-300x168.jpg", 
                "height": 168, 
                "mime-type": "image/jpeg", 
                "width": 300
            }, 
            "post-thumbnail": {
                "file": "1_n-220x126.jpg", 
                "height": 126, 
                "mime-type": "image/jpeg", 
                "width": 220
            }, 
            "thumbnail": {
                "file": "1_n-150x150.jpg", 
                "height": 150, 
                "mime-type": "image/jpeg", 
                "width": 150
            }
        }, 
        "width": 720
    }, 
    "author": "brooke", 
    "date": 1405106719000, 
    "ptype": "attachment", 
    "slug": "1_n", 
    "status": "inherit", 
    "title": "1_n"
} , "ThankYou305" : {
    "ID": 305, 
    "_wp_attached_file": "2014/07/ThankYou.jpg", 
    "_wp_attachment_metadata": {
        "file": "2014/07/ThankYou.jpg", 
        "height": 817, 
        "image_meta": {
            "aperture": 0, 
            "camera": "", 
            "caption": "", 
            "copyright": "", 
            "created_timestamp": 0, 
            "credit": "", 
            "focal_length": 0, 
            "iso": 0, 
            "shutter_speed": 0, 
            "title": ""
        }, 
        "sizes": {
            "expound-featured": {
                "file": "ThankYou-460x260.jpg", 
                "height": 260, 
                "mime-type": "image/jpeg", 
                "width": 460
            }, 
            "expound-mini": {
                "file": "ThankYou-50x50.jpg", 
                "height": 50, 
                "mime-type": "image/jpeg", 
                "width": 50
            }, 
            "large": {
                "file": "ThankYou-1024x742.jpg", 
                "height": 742, 
                "mime-type": "image/jpeg", 
                "width": 1024
            }, 
            "medium": {
                "file": "ThankYou-300x217.jpg", 
                "height": 217, 
                "mime-type": "image/jpeg", 
                "width": 300
            }, 
            "post-thumbnail": {
                "file": "ThankYou-220x126.jpg", 
                "height": 126, 
                "mime-type": "image/jpeg", 
                "width": 220
            }, 
            "thumbnail": {
                "file": "ThankYou-150x150.jpg", 
                "height": 150, 
                "mime-type": "image/jpeg", 
                "width": 150
            }
        }, 
        "width": 1126
    }, 
    "author": "brooke", 
    "date": 1405700491000, 
    "ptype": "attachment", 
    "slug": "thankyou", 
    "status": "inherit", 
    "title": "ThankYou"
} , "ThankYou309" : {
    "ID": 309, 
    "_wp_attached_file": "2014/07/ThankYou1.jpg", 
    "_wp_attachment_metadata": {
        "file": "2014/07/ThankYou1.jpg", 
        "height": 817, 
        "image_meta": {
            "aperture": 0, 
            "camera": "", 
            "caption": "", 
            "copyright": "", 
            "created_timestamp": 0, 
            "credit": "", 
            "focal_length": 0, 
            "iso": 0, 
            "shutter_speed": 0, 
            "title": ""
        }, 
        "sizes": {
            "expound-featured": {
                "file": "ThankYou1-460x260.jpg", 
                "height": 260, 
                "mime-type": "image/jpeg", 
                "width": 460
            }, 
            "expound-mini": {
                "file": "ThankYou1-50x50.jpg", 
                "height": 50, 
                "mime-type": "image/jpeg", 
                "width": 50
            }, 
            "large": {
                "file": "ThankYou1-1024x742.jpg", 
                "height": 742, 
                "mime-type": "image/jpeg", 
                "width": 1024
            }, 
            "medium": {
                "file": "ThankYou1-300x217.jpg", 
                "height": 217, 
                "mime-type": "image/jpeg", 
                "width": 300
            }, 
            "post-thumbnail": {
                "file": "ThankYou1-220x126.jpg", 
                "height": 126, 
                "mime-type": "image/jpeg", 
                "width": 220
            }, 
            "thumbnail": {
                "file": "ThankYou1-150x150.jpg", 
                "height": 150, 
                "mime-type": "image/jpeg", 
                "width": 150
            }
        }, 
        "width": 1126
    }, 
    "author": "brooke", 
    "date": 1405700898000, 
    "ptype": "attachment", 
    "slug": "thankyou-2", 
    "status": "inherit", 
    "title": "ThankYou"
} , "ourstory329" : {
    "ID": 329, 
    "_wp_attached_file": "2014/08/ourstory-copy.jpg", 
    "_wp_attachment_metadata": {
        "file": "2014/08/ourstory-copy.jpg", 
        "height": 639, 
        "image_meta": {
            "aperture": 0, 
            "camera": "", 
            "caption": "", 
            "copyright": "", 
            "created_timestamp": 0, 
            "credit": "", 
            "focal_length": 0, 
            "iso": 0, 
            "shutter_speed": 0, 
            "title": ""
        }, 
        "sizes": {
            "expound-featured": {
                "file": "ourstory-copy-460x260.jpg", 
                "height": 260, 
                "mime-type": "image/jpeg", 
                "width": 460
            }, 
            "expound-mini": {
                "file": "ourstory-copy-50x50.jpg", 
                "height": 50, 
                "mime-type": "image/jpeg", 
                "width": 50
            }, 
            "medium": {
                "file": "ourstory-copy-300x199.jpg", 
                "height": 199, 
                "mime-type": "image/jpeg", 
                "width": 300
            }, 
            "post-thumbnail": {
                "file": "ourstory-copy-220x126.jpg", 
                "height": 126, 
                "mime-type": "image/jpeg", 
                "width": 220
            }, 
            "thumbnail": {
                "file": "ourstory-copy-150x150.jpg", 
                "height": 150, 
                "mime-type": "image/jpeg", 
                "width": 150
            }
        }, 
        "width": 960
    }, 
    "author": "brooke", 
    "date": 1406914258000, 
    "ptype": "attachment", 
    "slug": "ourstory-copy", 
    "status": "inherit", 
    "title": "ourstory "
} , "643889_397649050305599_1488946965_n334" : {
    "ID": 334, 
    "_wp_attached_file": "2014/08/643889_397649050305599_1488946965_n.jpg", 
    "_wp_attachment_metadata": {
        "file": "2014/08/643889_397649050305599_1488946965_n.jpg", 
        "height": 417, 
        "image_meta": {
            "aperture": 0, 
            "camera": "", 
            "caption": "", 
            "copyright": "", 
            "created_timestamp": 0, 
            "credit": "", 
            "focal_length": 0, 
            "iso": 0, 
            "shutter_speed": 0, 
            "title": ""
        }, 
        "sizes": {
            "expound-featured": {
                "file": "643889_397649050305599_1488946965_n-460x260.jpg", 
                "height": 260, 
                "mime-type": "image/jpeg", 
                "width": 460
            }, 
            "expound-mini": {
                "file": "643889_397649050305599_1488946965_n-50x50.jpg", 
                "height": 50, 
                "mime-type": "image/jpeg", 
                "width": 50
            }, 
            "medium": {
                "file": "643889_397649050305599_1488946965_n-300x225.jpg", 
                "height": 225, 
                "mime-type": "image/jpeg", 
                "width": 300
            }, 
            "post-thumbnail": {
                "file": "643889_397649050305599_1488946965_n-220x126.jpg", 
                "height": 126, 
                "mime-type": "image/jpeg", 
                "width": 220
            }, 
            "thumbnail": {
                "file": "643889_397649050305599_1488946965_n-150x150.jpg", 
                "height": 150, 
                "mime-type": "image/jpeg", 
                "width": 150
            }
        }, 
        "width": 556
    }, 
    "author": "brooke", 
    "date": 1407262682000, 
    "ptype": "attachment", 
    "slug": "643889_397649050305599_1488946965_n", 
    "status": "inherit", 
    "title": "643889_397649050305599_1488946965_n"
} , "1098505_10201141821286586_1009766887_n335" : {
    "ID": 335, 
    "_wp_attached_file": "2014/08/1098505_10201141821286586_1009766887_n.jpg", 
    "_wp_attachment_metadata": {
        "file": "2014/08/1098505_10201141821286586_1009766887_n.jpg", 
        "height": 636, 
        "image_meta": {
            "aperture": 0, 
            "camera": "", 
            "caption": "", 
            "copyright": "", 
            "created_timestamp": 0, 
            "credit": "", 
            "focal_length": 0, 
            "iso": 0, 
            "shutter_speed": 0, 
            "title": ""
        }, 
        "sizes": {
            "expound-featured": {
                "file": "1098505_10201141821286586_1009766887_n-460x260.jpg", 
                "height": 260, 
                "mime-type": "image/jpeg", 
                "width": 460
            }, 
            "expound-mini": {
                "file": "1098505_10201141821286586_1009766887_n-50x50.jpg", 
                "height": 50, 
                "mime-type": "image/jpeg", 
                "width": 50
            }, 
            "medium": {
                "file": "1098505_10201141821286586_1009766887_n-300x198.jpg", 
                "height": 198, 
                "mime-type": "image/jpeg", 
                "width": 300
            }, 
            "post-thumbnail": {
                "file": "1098505_10201141821286586_1009766887_n-220x126.jpg", 
                "height": 126, 
                "mime-type": "image/jpeg", 
                "width": 220
            }, 
            "thumbnail": {
                "file": "1098505_10201141821286586_1009766887_n-150x150.jpg", 
                "height": 150, 
                "mime-type": "image/jpeg", 
                "width": 150
            }
        }, 
        "width": 960
    }, 
    "author": "brooke", 
    "date": 1407262687000, 
    "ptype": "attachment", 
    "slug": "1098505_10201141821286586_1009766887_n", 
    "status": "inherit", 
    "title": "1098505_10201141821286586_1009766887_n"
} , "1231487_527836603953509_24060599_n336" : {
    "ID": 336, 
    "_wp_attached_file": "2014/08/1231487_527836603953509_24060599_n.jpg", 
    "_wp_attachment_metadata": {
        "file": "2014/08/1231487_527836603953509_24060599_n.jpg", 
        "height": 689, 
        "image_meta": {
            "aperture": 0, 
            "camera": "", 
            "caption": "", 
            "copyright": "", 
            "created_timestamp": 0, 
            "credit": "", 
            "focal_length": 0, 
            "iso": 0, 
            "shutter_speed": 0, 
            "title": ""
        }, 
        "sizes": {
            "expound-featured": {
                "file": "1231487_527836603953509_24060599_n-460x260.jpg", 
                "height": 260, 
                "mime-type": "image/jpeg", 
                "width": 460
            }, 
            "expound-mini": {
                "file": "1231487_527836603953509_24060599_n-50x50.jpg", 
                "height": 50, 
                "mime-type": "image/jpeg", 
                "width": 50
            }, 
            "medium": {
                "file": "1231487_527836603953509_24060599_n-300x215.jpg", 
                "height": 215, 
                "mime-type": "image/jpeg", 
                "width": 300
            }, 
            "post-thumbnail": {
                "file": "1231487_527836603953509_24060599_n-220x126.jpg", 
                "height": 126, 
                "mime-type": "image/jpeg", 
                "width": 220
            }, 
            "thumbnail": {
                "file": "1231487_527836603953509_24060599_n-150x150.jpg", 
                "height": 150, 
                "mime-type": "image/jpeg", 
                "width": 150
            }
        }, 
        "width": 960
    }, 
    "author": "brooke", 
    "date": 1407262693000, 
    "ptype": "attachment", 
    "slug": "1231487_527836603953509_24060599_n", 
    "status": "inherit", 
    "title": "1231487_527836603953509_24060599_n"
} , "1378691_10201636223446331_1647156204_n337" : {
    "ID": 337, 
    "_wp_attached_file": "2014/08/1378691_10201636223446331_1647156204_n.jpg", 
    "_wp_attachment_metadata": {
        "file": "2014/08/1378691_10201636223446331_1647156204_n.jpg", 
        "height": 536, 
        "image_meta": {
            "aperture": 0, 
            "camera": "", 
            "caption": "", 
            "copyright": "", 
            "created_timestamp": 0, 
            "credit": "", 
            "focal_length": 0, 
            "iso": 0, 
            "shutter_speed": 0, 
            "title": ""
        }, 
        "sizes": {
            "expound-featured": {
                "file": "1378691_10201636223446331_1647156204_n-460x260.jpg", 
                "height": 260, 
                "mime-type": "image/jpeg", 
                "width": 460
            }, 
            "expound-mini": {
                "file": "1378691_10201636223446331_1647156204_n-50x50.jpg", 
                "height": 50, 
                "mime-type": "image/jpeg", 
                "width": 50
            }, 
            "medium": {
                "file": "1378691_10201636223446331_1647156204_n-300x167.jpg", 
                "height": 167, 
                "mime-type": "image/jpeg", 
                "width": 300
            }, 
            "post-thumbnail": {
                "file": "1378691_10201636223446331_1647156204_n-220x126.jpg", 
                "height": 126, 
                "mime-type": "image/jpeg", 
                "width": 220
            }, 
            "thumbnail": {
                "file": "1378691_10201636223446331_1647156204_n-150x150.jpg", 
                "height": 150, 
                "mime-type": "image/jpeg", 
                "width": 150
            }
        }, 
        "width": 960
    }, 
    "author": "brooke", 
    "date": 1407262701000, 
    "ptype": "attachment", 
    "slug": "1378691_10201636223446331_1647156204_n", 
    "status": "inherit", 
    "title": "1378691_10201636223446331_1647156204_n"
} , "colburnvideo_logo_web_high395" : {
    "ID": 395, 
    "_wp_attached_file": "2014/09/colburnvideo_logo_web_high.png", 
    "_wp_attachment_metadata": {
        "file": "2014/09/colburnvideo_logo_web_high.png", 
        "height": 550, 
        "image_meta": {
            "aperture": 0, 
            "camera": "", 
            "caption": "", 
            "copyright": "", 
            "created_timestamp": 0, 
            "credit": "", 
            "focal_length": 0, 
            "iso": 0, 
            "shutter_speed": 0, 
            "title": ""
        }, 
        "sizes": {
            "expound-featured": {
                "file": "colburnvideo_logo_web_high-460x260.png", 
                "height": 260, 
                "mime-type": "image/png", 
                "width": 460
            }, 
            "expound-mini": {
                "file": "colburnvideo_logo_web_high-50x50.png", 
                "height": 50, 
                "mime-type": "image/png", 
                "width": 50
            }, 
            "medium": {
                "file": "colburnvideo_logo_web_high-300x296.png", 
                "height": 296, 
                "mime-type": "image/png", 
                "width": 300
            }, 
            "post-thumbnail": {
                "file": "colburnvideo_logo_web_high-220x126.png", 
                "height": 126, 
                "mime-type": "image/png", 
                "width": 220
            }, 
            "thumbnail": {
                "file": "colburnvideo_logo_web_high-150x150.png", 
                "height": 150, 
                "mime-type": "image/png", 
                "width": 150
            }
        }, 
        "width": 556
    }, 
    "author": "brooke", 
    "date": 1409796441000, 
    "ptype": "attachment", 
    "slug": "colburnvideo_logo_web_high", 
    "status": "inherit", 
    "title": "colburnvideo_logo_web_high"
} , "2-1084604-328dfb5083b290bfd5d2e1f81f3b789b copy407" : {
    "ID": 407, 
    "_wp_attached_file": "2014/09/2-1084604-328dfb5083b290bfd5d2e1f81f3b789b-copy.png", 
    "_wp_attachment_metadata": {
        "file": "2014/09/2-1084604-328dfb5083b290bfd5d2e1f81f3b789b-copy.png", 
        "height": 168, 
        "image_meta": {
            "aperture": 0, 
            "camera": "", 
            "caption": "", 
            "copyright": "", 
            "created_timestamp": 0, 
            "credit": "", 
            "focal_length": 0, 
            "iso": 0, 
            "shutter_speed": 0, 
            "title": ""
        }, 
        "sizes": {
            "expound-mini": {
                "file": "2-1084604-328dfb5083b290bfd5d2e1f81f3b789b-copy-50x50.png", 
                "height": 50, 
                "mime-type": "image/png", 
                "width": 50
            }, 
            "post-thumbnail": {
                "file": "2-1084604-328dfb5083b290bfd5d2e1f81f3b789b-copy-170x126.png", 
                "height": 126, 
                "mime-type": "image/png", 
                "width": 170
            }, 
            "thumbnail": {
                "file": "2-1084604-328dfb5083b290bfd5d2e1f81f3b789b-copy-150x150.png", 
                "height": 150, 
                "mime-type": "image/png", 
                "width": 150
            }
        }, 
        "width": 170
    }, 
    "author": "brooke", 
    "date": 1409848099000, 
    "ptype": "attachment", 
    "slug": "2-1084604-328dfb5083b290bfd5d2e1f81f3b789b-copy", 
    "status": "inherit", 
    "title": "2-1084604-328dfb5083b290bfd5d2e1f81f3b789b copy"
} , "pricing409" : {
    "ID": 409, 
    "_wp_attached_file": "2014/01/pricing.jpg", 
    "_wp_attachment_metadata": {
        "file": "2014/01/pricing.jpg", 
        "height": 5000, 
        "image_meta": {
            "aperture": 0, 
            "camera": "", 
            "caption": "", 
            "copyright": "", 
            "created_timestamp": 0, 
            "credit": "", 
            "focal_length": 0, 
            "iso": 0, 
            "shutter_speed": 0, 
            "title": ""
        }, 
        "sizes": {
            "expound-featured": {
                "file": "pricing-460x260.jpg", 
                "height": 260, 
                "mime-type": "image/jpeg", 
                "width": 460
            }, 
            "expound-mini": {
                "file": "pricing-50x50.jpg", 
                "height": 50, 
                "mime-type": "image/jpeg", 
                "width": 50
            }, 
            "large": {
                "file": "pricing-1024x731.jpg", 
                "height": 731, 
                "mime-type": "image/jpeg", 
                "width": 1024
            }, 
            "medium": {
                "file": "pricing-300x214.jpg", 
                "height": 214, 
                "mime-type": "image/jpeg", 
                "width": 300
            }, 
            "post-thumbnail": {
                "file": "pricing-220x126.jpg", 
                "height": 126, 
                "mime-type": "image/jpeg", 
                "width": 220
            }, 
            "thumbnail": {
                "file": "pricing-150x150.jpg", 
                "height": 150, 
                "mime-type": "image/jpeg", 
                "width": 150
            }
        }, 
        "width": 7000
    }, 
    "author": "brooke", 
    "date": 1409850908000, 
    "ptype": "attachment", 
    "slug": "pricing", 
    "status": "inherit", 
    "title": "pricing"
} , "Thank you437" : {
    "ID": 437, 
    "_wp_attached_file": "2014/10/Thank-you.jpg", 
    "_wp_attachment_metadata": {
        "file": "2014/10/Thank-you.jpg", 
        "height": 360, 
        "image_meta": {
            "aperture": 0, 
            "camera": "", 
            "caption": "", 
            "copyright": "", 
            "created_timestamp": 0, 
            "credit": "", 
            "focal_length": 0, 
            "iso": 0, 
            "shutter_speed": 0, 
            "title": ""
        }, 
        "sizes": {
            "expound-featured": {
                "file": "Thank-you-460x260.jpg", 
                "height": 260, 
                "mime-type": "image/jpeg", 
                "width": 460
            }, 
            "expound-mini": {
                "file": "Thank-you-50x50.jpg", 
                "height": 50, 
                "mime-type": "image/jpeg", 
                "width": 50
            }, 
            "medium": {
                "file": "Thank-you-300x214.jpg", 
                "height": 214, 
                "mime-type": "image/jpeg", 
                "width": 300
            }, 
            "post-thumbnail": {
                "file": "Thank-you-220x126.jpg", 
                "height": 126, 
                "mime-type": "image/jpeg", 
                "width": 220
            }, 
            "thumbnail": {
                "file": "Thank-you-150x150.jpg", 
                "height": 150, 
                "mime-type": "image/jpeg", 
                "width": 150
            }
        }, 
        "width": 504
    }, 
    "author": "brooke", 
    "date": 1413146337000, 
    "ptype": "attachment", 
    "slug": "thank-you-2", 
    "status": "inherit", 
    "title": "Thank you"
} , "colburnvideo_staticimage.jpg558" : {
    "ID": 558, 
    "_wp_attached_file": "2015/02/colburnvideo_staticimage.jpg", 
    "_wp_attachment_context": "custom-header", 
    "_wp_attachment_is_custom_header": "expound", 
    "_wp_attachment_metadata": {
        "file": "2015/02/colburnvideo_staticimage.jpg", 
        "height": 154, 
        "image_meta": {
            "aperture": 0, 
            "camera": "", 
            "caption": "", 
            "copyright": "", 
            "created_timestamp": 0, 
            "credit": "", 
            "focal_length": 0, 
            "iso": 0, 
            "shutter_speed": 0, 
            "title": ""
        }, 
        "sizes": {
            "expound-featured": {
                "file": "colburnvideo_staticimage-460x154.jpg", 
                "height": 154, 
                "mime-type": "image/jpeg", 
                "width": 460
            }, 
            "expound-mini": {
                "file": "colburnvideo_staticimage-50x50.jpg", 
                "height": 50, 
                "mime-type": "image/jpeg", 
                "width": 50
            }, 
            "medium": {
                "file": "colburnvideo_staticimage-300x45.jpg", 
                "height": 45, 
                "mime-type": "image/jpeg", 
                "width": 300
            }, 
            "post-thumbnail": {
                "file": "colburnvideo_staticimage-220x126.jpg", 
                "height": 126, 
                "mime-type": "image/jpeg", 
                "width": 220
            }, 
            "thumbnail": {
                "file": "colburnvideo_staticimage-150x150.jpg", 
                "height": 150, 
                "mime-type": "image/jpeg", 
                "width": 150
            }
        }, 
        "width": 1020
    }, 
    "author": "brooke", 
    "date": 1423666547000, 
    "ptype": "attachment", 
    "slug": "colburnvideo_staticimage-jpg", 
    "status": "inherit", 
    "title": "colburnvideo_staticimage.jpg"
} }